everything_efu_gen.py
everything_efu_gen-0.0.3.dist-info/METADATA
everything_efu_gen-0.0.3.dist-info/WHEEL
everything_efu_gen-0.0.3.dist-info/entry_points.txt
everything_efu_gen-0.0.3.dist-info/top_level.txt
everything_efu_gen-0.0.3.dist-info/RECORD
