Metadata-Version: 2.1
Name: everything-efu-gen
Version: 0.0.3
Summary: Generator of Everything File List (EFU) files
Home-page: https://github.com/tobbez/everything-efu-gen
Author: tobbez
Author-email: tobbez@ryara.net
License: ISC
Keywords: voidtools,everything,efu
Classifier: Development Status :: 5 - Production/Stable
Classifier: License :: OSI Approved :: ISC License (ISCL)
Classifier: Programming Language :: Python :: 3
Classifier: Programming Language :: Python :: 3.4
Classifier: Programming Language :: Python :: 3.5
Classifier: Programming Language :: Python :: 3.6
Requires-Dist: ruamel.yaml
